{
    "countryName": "England",
    "countryLang": "english",
    "countryCode": "en",
    "status": "active",
    "labels": {
        "ruleDetails": "Rule Details",
        "eventsGlobal": "iOrder",
        "ruleAdmin": "Rule Admin",
        "rules": "Rules",
        "ruleName": "Rule Name",
        "ruleTag": "Rule Tag",
        "ruleDescription": "Rule Description",
        "dimension": "Dimension",
        "selectDimension": "Select Dimension",
        "attribute": "Attribute",
        "selectAttribute": "Select Attribute",
        "rootIdentifier": "Root Identifier",
        "ruleOutcome": "Rule Outcome",
        "value": "Value",
        "dashboard": "Dashboard",
        "gridRules": "Grid Rules",
        "complexRules": "Complex Rules",
        "relationalOperator": "Relational Operator",
        "rulesData": "Rules Data",
        "childCondition": "Child Condition",
        "response": "Response",
        "close": "Close",
        "done": "Done",
        "addRule": "Add Rule",
        "addResponses": "Add Responses",
        "addRuleData": "Add Rule Data",
        "enterBulkData": "Enter Bulk Data",
        "integrationTag": "Integration Tag",
        "defaultPayload": "default:payload",
        "back": "Back",
        "cancel": "Cancel",
        "testThisRule": "Test This Rule",
        "save": "Save",
        "result": "Result",
        "add": "Add",
        "more": "More",
        "operator": "Operator",
        "edit": "Edit",
        "search": "Search",
        "menu": "Menu",
        "logout": "Log Out",
        "settings": "Settings",
        "english": "English",
        "language": "Language",
        "german": "German",
        "editResponse": "Edit Response",
        "outcome": "Result",
        "genNewAPIKey":"Generate New API Key",
        "API":"API's",
        "go":"Go"
    },
    "errors": {
        "requiredField": "This field is required.",
        "ruleNameMax": "Rule Name should be max 45 chars.",
        "ruleDescMax": "Rule Description should be max 255 chars.",
        "ruleTagMax": "Rule Tag should be max 255 chars.",
        "ruleResultMax": "Rule Tag should be max 255 chars.",
        "ruleOutcomeMax": "Rule Outcome should be max 255 chars.",
        "rootIdentifierMax": "Root Identifier should be max 125 chars.",
        "rulesExecutedWithBelowMessages": "Rules executed with below messages"
    }
}